unbaffeld/__init__.py
unbaffeld/_version.py
unbaffeld/data/diii-d/169958_profiles.h5
unbaffeld/gpr/gpfit.py
unbaffeld/gpr/gpfitTF.py
unbaffeld/gpr/gpfit_file.py
unbaffeld/gpr/deprecated/gaussian_process.py
unbaffeld/gpr/deprecated/gp_framework.py
unbaffeld/gpr/deprecated/gp_function.py
unbaffeld/gpr/deprecated/kernel.py
unbaffeld/gpr/notebooks/TSFit.ipynb
unbaffeld/gpr/tests/test_file.py
unbaffeld/gpr/tests/test_fit.py
unbaffeld/gpr/workflow/gpr_workflow.py
unbaffeld/gpr/workflow/hmode.yml
unbaffeld/gpr/workflow/lmode.yml
unbaffeld/gpr/workflow/plot_comparisons.py
unbaffeld/gpr/workflow/plot_comparisons_genfiles.sh
unbaffeld/gpr/workflow/syndata.py
unbaffeld/gpr/workflow/syndata_workflow.py
UNBAFFELD-0.2.4.dist-info/AUTHORS.rst
UNBAFFELD-0.2.4.dist-info/LICENSE
UNBAFFELD-0.2.4.dist-info/METADATA
UNBAFFELD-0.2.4.dist-info/WHEEL
UNBAFFELD-0.2.4.dist-info/top_level.txt
UNBAFFELD-0.2.4.dist-info/RECORD
